ximgpdf.py
ximgpdf-0.0.3.dist-info/METADATA
ximgpdf-0.0.3.dist-info/WHEEL
ximgpdf-0.0.3.dist-info/entry_points.txt
ximgpdf-0.0.3.dist-info/licenses/LICENSE.txt
ximgpdf-0.0.3.dist-info/RECORD
