Metadata-Version: 2.3
Name: ximgpdf
Version: 0.0.3
Summary: Extract images from pdf
Project-URL: Documentation, https://github.com/paqira/ximgpdf
Project-URL: Issues, https://github.com/paqira/ximgpdf/issues
Project-URL: Source, https://github.com/paqira/ximgpdf
Author-email: Kentaro Tatsumi <paqira.2019@gmail.com>
License: MIT
License-File: LICENSE.txt
Keywords: image,jpeg,pdf,png
Classifier: License :: OSI Approved :: MIT License
Classifier: Programming Language :: Python
Classifier: Programming Language :: Python :: 3.9
Classifier: Programming Language :: Python :: 3.10
Classifier: Programming Language :: Python :: 3.11
Classifier: Programming Language :: Python :: 3.12
Classifier: Programming Language :: Python :: 3.13
Classifier: Programming Language :: Python :: Implementation :: CPython
Classifier: Programming Language :: Python :: Implementation :: PyPy
Requires-Python: >=3.9
Requires-Dist: click>=8.0.0
Requires-Dist: pymupdf>=1.0.0
